tomohiro/__init__.py
tomohiro/tomohiro.py
tomohiro/ability/__init__.py
tomohiro/ability/calculator.py
tomohiro/ability/clock.py
tomohiro/ability/information_about_assistant.py
tomohiro/ability/web_crawler.py
tomohiro_shell/__init__.py
tomohiro_shell/tomohiro_shell.py
ceo_tomohiro-0.0.2b0.dist-info/LICENSE
ceo_tomohiro-0.0.2b0.dist-info/METADATA
ceo_tomohiro-0.0.2b0.dist-info/WHEEL
ceo_tomohiro-0.0.2b0.dist-info/entry_points.txt
ceo_tomohiro-0.0.2b0.dist-info/top_level.txt
ceo_tomohiro-0.0.2b0.dist-info/RECORD
